ask4args/__init__.py
ask4args/__main__.py
ask4args/core.py
ask4args-0.3.0.dist-info/LICENSE
ask4args-0.3.0.dist-info/METADATA
ask4args-0.3.0.dist-info/WHEEL
ask4args-0.3.0.dist-info/top_level.txt
ask4args-0.3.0.dist-info/RECORD
