Metadata-Version: 2.1
Name: ask4args
Version: 0.3.0
Summary: Python-Fire-like, ask for function args by Terminal UI / GUI, ensuring the type annotation. Read more: https://github.com/ClericPy/ask4args.
Home-page: https://github.com/ClericPy/ask4args
Author: ClericPy
Author-email: clericpy@gmail.com
License: MIT License
Keywords: fire,REPL,Terminal UI
Platform: any
Classifier: License :: OSI Approved :: MIT License
Classifier: Programming Language :: Python :: 3
Classifier: Programming Language :: Python :: 3.7
Requires-Dist: PyInquirer
Requires-Dist: pysimplegui
Requires-Dist: pydantic
